he/__init__.py
he/colors.py
he/config.py
he/experiment.py
he/he.py
he/trial.py
he/util.py
he/workspace.py
hepy-0.0.2.dist-info/METADATA
hepy-0.0.2.dist-info/WHEEL
hepy-0.0.2.dist-info/entry_points.txt
hepy-0.0.2.dist-info/top_level.txt
hepy-0.0.2.dist-info/RECORD
