Metadata-Version: 2.1
Name: hepy
Version: 0.0.2
Summary: A tool to manage experiment
Home-page: https://github.com/JunguangJiang/Happy-Experiments/settings
Author: Junguang Jiang
License: UNKNOWN
Platform: UNKNOWN
Classifier: Programming Language :: Python :: 3
Classifier: License :: OSI Approved :: MIT License
Requires-Python: >=3.6
Requires-Dist: click
Requires-Dist: colorama
Requires-Dist: sh
Requires-Dist: jsonpickle
Requires-Dist: prettytable
Requires-Dist: pandas
